jsonsql/__init__.py
jsonsql/jsonsql.py
jsonsql2-1.0.0.dist-info/METADATA
jsonsql2-1.0.0.dist-info/WHEEL
jsonsql2-1.0.0.dist-info/licenses/LICENSE
jsonsql2-1.0.0.dist-info/RECORD
