Metadata-Version: 2.4
Name: JsonSQL2
Version: 1.0.0
Summary: A Python library for safe SQL query execution from JSON input with built-in validation and sanitization
Project-URL: Homepage, https://github.com/yashimself/JsonSQL
Project-URL: Issues, https://github.com/yashimself/JsonSQL/issues
Author: yashimself
License-File: LICENSE
Classifier: License :: OSI Approved :: MIT License
Classifier: Operating System :: OS Independent
Classifier: Programming Language :: Python :: 3
Classifier: Programming Language :: Python :: 3.10
Classifier: Programming Language :: Python :: 3.11
Classifier: Programming Language :: Python :: 3.12
Requires-Python: >=3.10
